{
  "home": {
    "home": "Home",
    "headerTitleFull": "Your Solutions, Overlogic.",
    "headerTitleFull2": "Your Vision, Our logic.",
    "headerTitle": ["Your ", "vision, ", "our ", "  logic."],
    "headerTitle2": ["Your ", "solutions, ", "Over", "logic."],
    "headerDesc": [
      "Trusted",
      "software development",
      "agency committed to delivering high-quality digital solutions"
    ],
    "orderNow": "Order Now",
    "trustedByLeadingTeam": "Trusted By Leading Company",
    "projects": {
      "title": "Our Latest Projects",
      "seeMore": "See full showcase",
      "data": [
        {
          "title": "UMS IID",
          "description": "Innovation competition and exhibition at Universitas Muhammadiyah Surakarta that took place over 5 days.",
          "company": "umsIidLogo",
          "category": "International Events",
          "platform": "Web",
          "image": "umsiid",
          "link": "https://ums-iid.com/"
        },
        {
          "title": "Anugerah Powder Coating",
          "description": "The best coating service with high quality to protect and beautify your metal products.",
          "company": "anugerahLogo",
          "category": "Company Profile",
          "platform": "Web",
          "image": "anugerah",
          "link": "https://anugerahpowdercoating.com/"
        },
        {
          "title": "Pineleaf Care",
          "description": "Premium Care Brand engaged in Product Development and Retail Sales of shoe cleaning and care soap (Shoe Cleaner) established on March 7, 2015 in Surakarta City.",
          "company": "pineleafLogo",
          "category": "Company Profile",
          "platform": "Web",
          "image": "pineleaf",
          "link": "https://pineleaf.id/"
        }
      ]
    },
    "testimonials": {
      "title": "Customer Testimonials - How Overlogic's Solutions Drive Success and Innovation",
      "subTitle": "Explore the Impact of Overlogic's Innovative Solutions and How They Have Helped Our Clients Achieve Sustainable Growth, Efficiency, and Success in Their Industries",
      "reviews": [
        {
          "name": "Josumaru",
          "username": "@josurou",
          "body": "Overlogic is indeed beyond logic, I can't say words",
          "img": "https://avatar.vercel.sh/josuro"
        },
        {
          "name": "Josumaru",
          "username": "@josurou",
          "body": "Overlogic is indeed beyond logic, I can't say words",
          "img": "https://avatar.vercel.sh/josuro"
        },
        {
          "name": "Josumaru",
          "username": "@josurou",
          "body": "Overlogic is indeed beyond logic, I can't say words",
          "img": "https://avatar.vercel.sh/josuro"
        },
        {
          "name": "Josumaru",
          "username": "@josurou",
          "body": "Overlogic is indeed beyond logic, I can't say words",
          "img": "https://avatar.vercel.sh/josuro"
        },
        {
          "name": "Josumaru",
          "username": "@josurou",
          "body": "Overlogic is indeed beyond logic, I can't say words",
          "img": "https://avatar.vercel.sh/josuro"
        },
        {
          "name": "Josumaru",
          "username": "@josurou",
          "body": "Overlogic is indeed beyond logic, I can't say words",
          "img": "https://avatar.vercel.sh/josuro"
        }
      ]
    },
    "services": {
      "title": "Build Your Business Dominate the Market , Beat Your Competitors with Overlogic service",
      "subTitle": "Trust your application development and maintenance to us, all features will be quickly created with modern technology and security.",
      "more": "Learn more",
      "trusted": {
        "title": "Trusted",
        "subTitle": "Pineleafcare, UMS IID, Anugerah Powder Coating Blora trust us as their IT partner in increasing their productivity in business and limited events."
      },
      "price": {
        "title": "Affordable Price",
        "subTitle": "Get a good deal by contacting the Overlogic ID team and get up to 40% discount"
      },
      "seo": {
        "title": "Search Engine Optimalization",
        "subTitle": "Make your website searchable on the internet and at the top and boost your business with Overlogic Universe."
      },
      "performance": {
        "title": "Performance",
        "subTitle": "Increase the speed of your applications and avoid system failures in your business"
      },
      "security": {
        "title": "Security",
        "subTitle": "Protect your sensitive data and protect your customers' information with our advanced security measures"
      },
      "business": {
        "title": "Conquer the World with Your Business: It's Your Time to Shine!",
        "subTitle": "The world needs to know—this is your era. Unleash your power and let your business shake the world! 🌍✨"
      },
      "chart": [
        { "stats": "Performance", "range": 100 },
        { "stats": "Price", "range": 20 },
        { "stats": "SEO", "range": 100 },
        { "stats": "Security", "range": 100 },
        { "stats": "Speed", "range": 100 },
        { "stats": "Full Support", "range": 100 }
      ],
      "education": {
        "title": "Technology Education for the Future",
        "subTitle": "We don't just build software, we share knowledge. Our training programs and workshops help individuals and teams master the latest technologies."
      },
      "innovation": {
        "title": "Limitless Innovation",
        "subTitle": "We continuously explore emerging technologies like AI, Blockchain, and Cloud Computing to deliver smarter and more efficient software solutions."
      }
    },
    "faq": {
      "title": "Discover more about our logic through this Frequently Asked Question",
      "subTitle": "Find answers to common inquiries and dive deeper into the logic behind our services with this comprehensive FAQ section.",
      "faqData": [
        {
          "question": "What is Overlogic",
          "answer": "Overlogic is a trusted software development agency that delivers solutions through deep thinking, innovation, and modern technology, and supports efficient, inclusive, and sustainable digital transformation."
        },
        {
          "question": "What services does Overlogic provide?",
          "answer": "Overlogic offers web development, app development, UI/UX design, and software development partnership services tailored to meet your business needs."
        },
        {
          "question": "How can I contact Overlogic for a project inquiry?",
          "answer": "You can place an order directly on our website using the available packages. If you have special requests, feel free to contact us at email@overlogicuniverse.com."
        },
        {
          "question": "What industries does Overlogic serve?",
          "answer": "Overlogic serves various industries, including education, healthcare, retail, and more. Our solutions are customized to fit different business sectors."
        },
        {
          "question": "Does Overlogic provide post-development support?",
          "answer": "Yes, we provide comprehensive post-development support and maintenance to ensure your digital solutions perform seamlessly."
        },
        {
          "question": "How long does it take for a project to be completed?",
          "answer": "Project timelines vary based on complexity and requirements. After an initial consultation, we provide an estimated timeline tailored to your project."
        }
      ]
    }
  },
  "company": {
    "common": {
      "readMore": "Read more"
    },
    "company": "Company",
    "header": {
      "aboutOverlogicUniverse": "About Overlogic Universe",
      "title": "Building the Digital World, Embracing the Future",
      "subTitle": [
        "Overlogic Universe was founded with a passion to bring revolutionary changes to the digital world. Since 2024, we have been helping individuals and companies turn their visions into reality through smart and innovative digital solutions.",
        "Overlogic's mission is to be a trusted software development agency that provides solutions through deep, innovative, and modern technology-based thinking, and supports efficient, inclusive, and sustainable digital transformation."
      ]
    },
    "visionMission": {
      "title": "Overlogic Universe Helps Businesses Solve Many Problems",
      "subTitle": "Through technological innovation and strategic approaches, Overlogic Universe is committed to helping businesses tackle challenges, create new opportunities.",
      "visionMision": [
        {
          "title": "Innovation",
          "subTitle": "Developing responsive, secure, and sustainable software solutions that adapt to technological changes and client needs."
        },
        {
          "title": "Experience",
          "subTitle": "Delivering innovative and user-focused digital experiences by blending creative design and the latest technology."
        },
        {
          "title": "Collaboration",
          "subTitle": "Fostering a collaborative and inclusive work environment that supports individual and team growth through skill development and future technologies."
        },
        {
          "title": "Satisfaction",
          "subTitle": "Prioritizing client satisfaction with a transparent, flexible, and value-based approach to every partnership."
        },
        {
          "title": "Security",
          "subTitle": "Ensuring product security professionally."
        }
      ]
    },
    "team": {
      "title": "Meet the Overlogic Team, Driving Your Business Forward",
      "subTitle": "Our unity is the foundation of your success",
      "members": {
        "rafli": {
          "nickname": "Rafli",
          "name": "Muhammad Rafli Silehu",
          "intro": "As a Mobile Developer, I have experience in independent projects and relevant training using Kotlin Android, especially Flutter in project development. I am always passionate about creating mobile applications that provide a pleasant experience for users. I also have skills in web development and have founded a software development agency called Overlogic that can provide opportunities for members to gain experience in working on real projects.",
          "role": "Software Engineer",
          "linkedin": "https://www.linkedin.com/in/raflisilehu/",
          "github": "https://github.com/zakoraa/",
          "instagram": "https://www.instagram.com/raflisilehu_/"
        },
        "ogya": {
          "nickname": "OGYA",
          "name": "Ogya Rajendra",
          "intro": "Hello, I'm Ogya Rajendra, a Web Developer & UI/UX Designer passionate about creating modern, functional, and user-centered digital experiences. I specialize in front-end development and intuitive interface design, ensuring websites are visually appealing, responsive, and easy to use.  With experience in news portals, e-learning platforms, and e-commerce websites, I combine technical expertise with design thinking to build engaging and high-performing web applications. I am always exploring new technologies and UI/UX trends to craft seamless and effective user experiences.",
          "role": "Front End, Designer, Social Media Specialist",
          "linkedin": "www.linkedin.com/in/ogya-rajendra/",
          "github": "https://github.com/Oradra19/",
          "instagram": "www.instagram.com/ogyrjndra_/"
        },
        "chandra": {
          "nickname": "Chandra",
          "name": "Muhammad Chandra Aditya",
          "intro": "Hello, I'm Chandra.\nMy journey into programming started at a young age. While most kids were playing games, I was fascinated by the idea of ​​how the game work, from simply modifying game resources or modifying codes that I often play to get different experiences and just to see what different things would happen.  Little did I know, these small explorations would lead me into a passion for technology. As I grew, This curiosity eventually led me to pursue a degree in Informatics. I've learned various aspects of programming that I didn't know before, from web development that allows me to create interactive sites, to mobile application development that provides a complete user experience. ach journey in this field opened up new insights into how technology can be used to solve real-world problems and create innovative solutions that have impact in reality.  Of course, it was impossible to connect the dots looking forward when I was a kid. . However, it is very, very clear looking back a few years later. We may not always know where our steps will take us, but trust me—the dots will connect in time. You have to trust in God and also your ability to believe—whether it's in your instincts, destiny, life, or karma. This approach has never let me down, and has made a big difference in my life. I learned that loving what we do is the greatest fuel to keep moving forward.",
          "role": "Mobile Developer, Front-End Web Developer, Cyber Security Enthusiast",
          "linkedin": "www.linkedin.com/in/chandra-a-2a118a137",
          "github": "https://github.com/MCHAN07",
          "instagram": "www.instagram.com/chandradityaaaa"
        },
        "joko": {
          "nickname": "JOKO",
          "name": "Joko Supriyanto",
          "intro": "Passionate Android and Web Developer with a strong foundation in database management, software development, and project management. Currently pursuing a Bachelor's degree in Informatics at Muhammadiyah University of Surakarta, where I also contribute as a Laboratory Assistant, guiding students in programming, database systems, and operating systems.\nAs part of the Google Developer Student Clubs Core Team, I actively create and manage AI-focused events to enhance community knowledge. Driven to build innovative solutions and foster growth in the tech ecosystem.",
          "role": "Mobile Developer, Front-End Web Developer",
          "linkedin": "www.linkedin.com/in/josumaru",
          "github": "https://github.com/Josumaru",
          "instagram": "www.instagram.com/josurou"
        },
        "rizky": {
          "nickname": "Rizky",
          "name": "Rizky Maulana Saputra",
          "intro": "Hello! I am an undergraduate student majoring in Informatics at Universitas Muhammadiyah Surakarta and working as a Front-End Developer at Overlogic. I have a strong interest in web development, particularly in front-end, as well as artificial intelligence and machine learning. Currently, I am also working on several projects involving Augmented Reality and Virtual Reality technologies. With this experience, I hope to continue growing and making a positive impact in the tech industry",
          "role": "Front end developer, AI/ML Engineer",
          "linkedin": "https://www.linkedin.com/in/rizky-maulana-saputra",
          "github": "https://github.com/RizkyMlana",
          "instagram": "https://www.instagram.com/rizkymlaana"
        },
        "gilang": {
          "nickname": "Gilang",
          "name": "Gilang Sri Nayaka",
          "intro": "I am a student of Informatics Engineering at Universitas Muhammadiyah Surakarta. I have a deep interest in UI/UX Design and Front-End Development, and I always strive to learn and grow through various projects. Currently, I have completed the Bangkit 2024 Batch 2 program on the Mobile Development track.  I use Figma as my main tool for UI/UX design and am currently deepening my skills in Adobe XD and Adobe Illustrator. With a focus on user experience, I strive to create applications that are intuitive, engaging, and have a positive impact. I believe that good design is not only about aesthetics, but also about functionality and user convenience.",
          "role": "UI/UX Designer, Frontend, Android Developer",
          "linkedin": "https://www.linkedin.com/in/gilangsrinayaka",
          "github": "https://github.com/GilangSN23",
          "instagram": "https://www.instagram.com/gilangsn_gsn"
        },
        "afrizal": {
          "nickname": "Afrizal",
          "name": "Afrizal Putra Pratama",
          "intro": "Hey, I'm Afrizal Putra Pratama! I'm an IT student at UMS, and I'm super passionate about UI Design. I'm currently learning and experimenting with cool user interface designs. I'm stoked to meet fellow design enthusiasts, share ideas, and learn from each other. Looking forward to connecting and creating something amazing together!",
          "role": "UI Designer ",
          "linkedin": "https://www.linkedin.com/in/afrizal-putra-pratama-24678128b",
          "github": "https://github.com/ums-l200220262",
          "instagram": "https://www.instagram.com/afzapp"
        }
      }
    },
    "gallery": {
      "title": "Overlogic Gallery, A Portrait of Innovation and Togetherness",
      "subTitle": "Every moment is part of our journey to success"
    }
  },
  "pricing": {
    "title": "Pricing Plans for every stage of Your Vision",
    "subTitle": "Explore our pricing plans designed to adapt to your unique goals, ensuring every stage of your vision is supported with modern technology and seamless execution",
    "flexible": "Flexible",
    "pricing": "Pricing",
    "from": "From",
    "order": "Order",
    "basic": {
      "title": "Basic",
      "subTitle": "Ignite your business' first steps in the digital world with Overlogic.",
      "features": [
        "Customizable designs",
        "Enhanced collaboration tools",
        "Priority support",
        "Basic maintenance and updates"
      ]
    },
    "professional": {
      "title": "Professional",
      "subTitle": "Increase your business visibility and performance with professional technology. For businesses that want to grow and shine in the digital world.",
      "features": [
        "All basic package benefits",
        "High scalability",
        "Performance Enhancement",
        "Backup Support"
      ]
    },
    "advanced": {
      "title": "Advanced",
      "subTitle": "Exclusive and flexible solutions for your business's specific technology needs.",
      "features": [
        "Benefit from basic & professional packages ",
        "Extended maintenance and updates",
        "Premium support and training",
        "Customized software solutions"
      ]
    }
  },
  "showcase": {
    "common": {
      "seeMore": "See more"
    },
    "showcase": "Portfolio",
    "title": "Smart Steps Towards Digitalization",
    "subTitle": "Discover how our solutions can transform the way you run your business.",
    "type": {
      "web": "Website",
      "mobile": "Mobile Apps",
      "ai": "Artificial Intelligence"
    },
    "projects": {
      "umsiid": {
        "title": "UMS IID",
        "description": "UMS International Innovation Day is an innovation competition and exhibition at Universitas Muhammadiyah Surakarta that took place over 5 days. The event encouraged the creative ideas of national and international students with the theme of SDG 3, and included an opening ceremony, exhibition, presentation, judging, innovation talk, and awarding. The event involves academics, students, and communities to create sustainable solutions and strengthen UMS' role at the international level."
      },
      "pinleaf": {
        "title": "Pinleaf",
        "description": "Pineleafcare is the pioneer of shoe, bag and stroller care solutions in Indonesia, Pineleafcare Franchise! The best solution for shoe, bag and stroller care business with training support and professional partnership system."
      },
      "anugerah": {
        "title": "Anugerah Powder Coating Blora",
        "description": "Premium Powder Coating services not only enhance the beauty of metal surfaces, but also provide strong protection from pollution, fine scratches, and oxidation. Experience the perfect combination of durability and shine with our durable coatings, ensuring maximum protection for the long term."
      },
      "josumaru": {
        "title": "Josumaru",
        "description": "A web portfolio created by one of Overlogic Universe's developers that was created by combining Next.JS, TypeScript, React, Tailwind CSS, and Aceternity UI."
      },
      "vido": {
        "title": "VIDO - Virtual Doctor",
        "description": "Modern Healthcare Solutions Considerate and cute Assistant Best of the best. Now you can consult anywhere and everywhere with a cute and caring assitant, with us of course."
      },
      "sheesh": {
        "title": "SHEESH",
        "description": "SHEESH is an intelligent hybrid market analysis mobile app designed to empower MSMEs with advanced tools for customer segmentation, trend analysis, and sales prediction. Powered by machine learning frameworks like Scikit-learn and TensorFlow, the app delivers data-driven insights to help businesses make informed decisions. Built with Flutter for a seamless user experience and Firebase for a secure and scalable backend, SHEESH provides comprehensive market analysis and customized heuristic guidance to drive growth and efficiency for small and medium enterprises."
      },
      "parky": {
        "title": "Parky",
        "description": "Parky is an Android mobile application designed to streamline student parking management by using a QR Code scanning system to record entry and exit times. Built with Java for Android and integrated with Firebase, Parky ensures efficient data handling and real-time updates. The app includes key features such as a QR Code Scanner for automated check-ins and check-outs, User Authentication for secure access, and CRUD (Create, Read, Update, Delete) functionalities to manage user data. Developed as a final project for a mobile development course, Parky enhances parking efficiency and security through modern mobile technology."
      },
      "fospresence": {
        "title": "Fospresence",
        "description": "Fospresence is a mobile application designed to streamline attendance tracking for participants in FOSTI UMS work programs using a QR Code scanning system. Developed with Flutter and powered by Firebase, the app ensures efficient and secure attendance recording. Key features include a QR Code Scanner for quick check-ins, an Excel Exporter for generating attendance reports, and CRUD (Create, Read, Update, Delete) functionalities for managing user data. By leveraging modern mobile technology, Fospresence simplifies attendance management, improves data accuracy, and enhances the overall efficiency of organizational events."
      },
      "fostifest": {
        "title": "FOSTIFEST 2024 WEB",
        "description": "FOSTIFEST 2024 is a web-based platform designed to facilitate participant registration for workshops and competitions at FOSTIFEST 2024. Built with Next.js and powered by Supabase, the platform provides a seamless user experience with features including a dynamic landing page, secure authentication, and an intuitive registration system for competition participants. Users can upload payment proof via image files and submit competition entries through Google Drive links, ensuring a smooth and efficient registration process. By leveraging modern web technologies, FOSTIFEST 2024 enhances accessibility and streamlines event management for participants and organizers alike."
      },
      "nusaira": {
        "title": "NusAIra",
        "description": "NusAIra is an AI-based platform designed to assist farmers in monitoring and managing pond conditions. NusAIra's main objectives are to improve operational efficiency, reduce the risk of harvest failure, and provide data-driven recommendations for catfish farming optimization. NusAIra also has AI technology to predict catfish market prices and a chatbot service, as well as an e-book library aimed at helping beginner catfish farmers.\nTechnology used\nNode.js + Express.js\nClever Cloud\nPython (TensorFlow / Scikit-learn)\nPandas & NumPy\nReact + Next.js\nDialogflow / Rasa\nNode.js\nKey Features\n✅ Market Price Prediction\n✅ Interactive Chatbot\n✅ E-Book Library \n✅ User Management\nPurpose & Benefits\n📌 Improve the efficiency of aquaculture with data-driven monitoring.\n📌 Support the sustainability of the fisheries industry through digital technology innovation.\n📌 Help beginner catfish farmers gain more knowledge through relevant e-books.\n📌 Provide market price predictions that help farmers in planning product selling prices.\n📌 Simplify communication with a chatbot that provides direct information about markets and products."
      }
    }
  },
  "order": {
    "title": "Tell Us Your Needs",
    "subTitle": "Overlogic Will Always Be There to Fulfill Your Needs.",
    "next": "Next",
    "prev": "Previous",
    "services": [
      "Custom Software Development",
      "API Development & Integration",
      "E-commerce Solutions",
      "Blockchain Development",
      "DevOps & Cloud Solutions",
      "Graphic Design",
      "Logo Design",
      "Video Editing & Animation",
      "Motion Graphics",
      "SEO Optimization",
      "Content Writing",
      "Machine Learning Models",
      "Business Intelligence",
      "Training & Workshops",
      "IT Consultation",
      "Product Management",
      "Cybersecurity Services"
    ],
    "budgets": [
      "Under 350,000 IDR",
      "350,000 IDR - Basic",
      "750,000 IDR - Professional",
      "1,250,000 IDR - Advanced",
      "5,000,000+ IDR",
      "10,000,000+ IDR",
      "50,000,000+ IDR"
    ],
    "form": {
      "name": {
        "title": "What's Your Name, Superstar?",
        "placeholder": "Tell us your legendary name",
        "value": "Name",
        "error": "Name must be at least 2 characters and up to 128 characters."
      },
      "email": {
        "title": "Your Email Address",
        "placeholder": "Drop your best email here",
        "value": "Email",
        "error": "Please enter a valid email address (max 64 characters)."
      },
      "phone": {
        "title": "How Can We Reach You?",
        "placeholder": "Your magic digits go here!",
        "value": "Phone Number",
        "error": "Phone number must be between 7 and 16 digits."
      },
      "company": {
        "title": "Your Company Name",
        "placeholder": "What's your company's awesome name?",
        "value": "Company Name",
        "error": "Company name must be between 2 and 128 characters."
      },
      "project": {
        "title": "Your Project Name",
        "placeholder": "What's the next big thing you're working on?",
        "value": "Project Name",
        "error": "Project name must be between 2 and 256 characters."
      },
      "position": {
        "title": "Your Role/Position",
        "placeholder": "What's your superpower in the team?",
        "value": "Position",
        "error": "Position must be at least 2 characters and up to 128 characters."
      },
      "services": {
        "title": "What Services Do You Need?",
        "value": "Services",
        "error": "Please select at least one service (max 5 services)."
      },
      "budget": {
        "title": "What's Your Budget Range?",
        "value": "Budget",
        "error": "Select at least 1 budget (max 64 characters)."
      },
      "brief": {
        "title": "Project Brief Link",
        "placeholder": "Drop your project brief link here",
        "value": "Brief",
        "error": "Brief must be at least 2 characters and up to 256 characters."
      },
      "additional": {
        "title": "Additional Information",
        "placeholder": "Anything else we should know? Tell us!",
        "value": "Additional Info",
        "error": "Additional information must be at least 2 characters and up to 256 characters."
      },
      "question": {
        "title": "Got Any Questions?",
        "placeholder": "Ask us anything, we love questions!",
        "value": "Question",
        "error": "Question must be at least 2 characters and up to 256 characters."
      },
      "testimony": {
        "title": "Testimony",
        "placeholder": "Share your experience with us!",
        "value": "Testimony",
        "error": "Testimony must be at least 2 characters and up to 512 characters."
      },
      "instagram": {
        "title": "Instagram",
        "placeholder": "Enter your Instagram username",
        "value": "Instagram",
        "error": "Instagram username must be at least 2 characters and up to 64 characters."
      },
      "x": {
        "title": "X (Twitter)",
        "placeholder": "Enter your X (Twitter) username",
        "value": "X (Twitter)",
        "error": "X (Twitter) username must be at least 2 characters and up to 64 characters."
      }
    },
    "testimonial_permission": {
      "title": "Allow Us to Showcase Your Testimony",
      "description": "We'd be happy to share your testimony to inspire others."
    },
    "toast": {
      "error": {
        "value": "Error Occurred!",
        "desc": "Oops! Something went wrong. Please try again."
      },
      "error_network": {
        "value": "Network Issue",
        "desc": "Your internet connection seems unstable. Please make sure you're connected properly."
      },
      "error_step": {
        "value": "Step Incomplete",
        "desc": "Some steps are still pending. Please make sure all information is filled out correctly."
      },
      "success": {
        "value": "Success!",
        "desc": "Your request has been processed successfully."
      }
    },
    "loading": "Loading...",
    "sending": "Sending...",
    "submit": "Submit",
    "thankYou": {
      "title": "Thank You!",
      "message": "We will contact you soon",
      "button": "Home",
      "feedback": "Your words mean the world to us."
    },
    "review": "Review Your Data"
  },
  "common": {
    "whatsapp": {
      "message": "Hey there! 👋 I'm interested in Overlogic's services and wanted to ask a few things.\n\n✨ *Questions:*\n1. ...\n2. ...\n\nLet me know when you have a moment. Thanks a lot! 😊"
    },
    "footer": {
      "links": [
        {
          "title": "Service",
          "subtitles": [
            {
              "name": "Website Development",
              "url": ""
            },
            {
              "name": "Mobile Development",
              "url": ""
            },
            {
              "name": "Backend Development",
              "url": ""
            },
            {
              "name": "AI Development",
              "url": ""
            }
          ]
        },
        {
          "title": "Project",
          "subtitles": [
            {
              "name": "UMS IID",
              "url": "https://ums-iid.com/"
            },
            {
              "name": "Anugerah",
              "url": "https://anugerahpowdercoating.com/"
            },
            {
              "name": "Pineleaf",
              "url": "https://pineleaf.id/"
            }
          ]
        },
        {
          "title": "Overlogic",
          "subtitles": [
            {
              "name": "Websites",
              "url": "https://overlogic.id"
            },
            {
              "name": "Instagram",
              "url": "https://www.instagram.com/overlogic.id/"
            },
            {
              "name": "Linkedin",
              "url": "https://www.linkedin.com/in/overlogic"
            }
          ]
        },
        {
          "title": "Domain",
          "subtitles": [
            {
              "name": "overlogic.io",
              "url": "https://overlogic.io"
            }
          ]
        }
      ],
      "status": {
        "up": "All system operational",
        "hasIissues": "Some systems experiencing issues",
        "underMaintenance": "System under maintenance",
        "loading": "Loading status"
      },
      "right": "All rights reserved"
    }
  }
}
